exonware/xsystem/__init__.py
exonware/xsystem/config/__init__.py
exonware/xsystem/config/defaults.py
exonware/xsystem/config/logging.py
exonware/xsystem/config/logging_setup.py
exonware/xsystem/config/performance.py
exonware/xsystem/config/performance_modes.py
exonware/xsystem/http/__init__.py
exonware/xsystem/http/client.py
exonware/xsystem/io/__init__.py
exonware/xsystem/io/atomic_file.py
exonware/xsystem/io/path_manager.py
exonware/xsystem/monitoring/__init__.py
exonware/xsystem/monitoring/error_recovery.py
exonware/xsystem/monitoring/memory_monitor.py
exonware/xsystem/monitoring/metrics.py
exonware/xsystem/monitoring/performance_monitor.py
exonware/xsystem/monitoring/performance_validator.py
exonware/xsystem/patterns/__init__.py
exonware/xsystem/patterns/context_manager.py
exonware/xsystem/patterns/dynamic_facade.py
exonware/xsystem/patterns/handler_factory.py
exonware/xsystem/patterns/import_registry.py
exonware/xsystem/patterns/object_pool.py
exonware/xsystem/performance/__init__.py
exonware/xsystem/performance/manager.py
exonware/xsystem/plugins/__init__.py
exonware/xsystem/plugins/base.py
exonware/xsystem/runtime/__init__.py
exonware/xsystem/runtime/env.py
exonware/xsystem/runtime/reflection.py
exonware/xsystem/security/__init__.py
exonware/xsystem/security/crypto.py
exonware/xsystem/security/path_validator.py
exonware/xsystem/security/resource_limits.py
exonware/xsystem/serialization/__init__.py
exonware/xsystem/serialization/aSerialization.py
exonware/xsystem/serialization/bson.py
exonware/xsystem/serialization/cbor.py
exonware/xsystem/serialization/configparser.py
exonware/xsystem/serialization/csv.py
exonware/xsystem/serialization/dbm.py
exonware/xsystem/serialization/formdata.py
exonware/xsystem/serialization/iSerialization.py
exonware/xsystem/serialization/json.py
exonware/xsystem/serialization/marshal.py
exonware/xsystem/serialization/msgpack.py
exonware/xsystem/serialization/multipart.py
exonware/xsystem/serialization/pickle.py
exonware_xsystem-0.0.2.dist-info/METADATA
exonware_xsystem-0.0.2.dist-info/WHEEL
exonware_xsystem-0.0.2.dist-info/RECORD
