Metadata-Version: 2.4
Name: exonware-xsystem
Version: 0.0.2
Summary: Enterprise-grade Python framework with AI-powered performance optimization, 17 serialization formats, military-grade security, automatic memory leak prevention, circuit breakers, and production monitoring - replaces 50+ dependencies
Project-URL: Homepage, https://exonware.com
Project-URL: Repository, https://github.com/exonware/xsystem
Project-URL: Documentation, https://github.com/exonware/xsystem#readme
Author-email: "Eng. Muhammad AlShehri" <connect@exonware.com>
License: MIT
Keywords: ai-optimization,bson,cbor,circuit-breaker,crypto,enterprise,exonware,framework,json,memory-management,monitoring,msgpack,object-pool,performance,security,serialization,threading,yaml
Classifier: Development Status :: 4 - Beta
Classifier: Intended Audience :: Developers
Classifier: Intended Audience :: Information Technology
Classifier: Intended Audience :: System Administrators
Classifier: License :: OSI Approved :: MIT License
Classifier: Operating System :: OS Independent
Classifier: Programming Language :: Python :: 3
Classifier: Programming Language :: Python :: 3.13
Classifier: Topic :: Database
Classifier: Topic :: Internet :: WWW/HTTP
Classifier: Topic :: Security :: Cryptography
Classifier: Topic :: Software Development :: Libraries :: Python Modules
Classifier: Topic :: System :: Monitoring
Classifier: Topic :: System :: Systems Administration
Requires-Python: >=3.13
Provides-Extra: all
Requires-Dist: cbor2>=5.0.0; extra == 'all'
Requires-Dist: cryptography>=41.0.0; extra == 'all'
Requires-Dist: dicttoxml>=1.7.4; extra == 'all'
Requires-Dist: httpx>=0.24.0; extra == 'all'
Requires-Dist: importlib-metadata>=6.0.0; (python_version < '3.8') and extra == 'all'
Requires-Dist: msgpack>=1.0.0; extra == 'all'
Requires-Dist: pymongo>=4.0.0; extra == 'all'
Requires-Dist: pyyaml>=6.0; extra == 'all'
Requires-Dist: tomli-w>=1.0.0; extra == 'all'
Requires-Dist: xmltodict>=0.12.0; extra == 'all'
Provides-Extra: bson
Requires-Dist: pymongo>=4.0.0; extra == 'bson'
Provides-Extra: cbor
Requires-Dist: cbor2>=5.0.0; extra == 'cbor'
Provides-Extra: crypto
Requires-Dist: cryptography>=41.0.0; extra == 'crypto'
Provides-Extra: dev
Requires-Dist: black>=23.0.0; extra == 'dev'
Requires-Dist: isort>=5.12.0; extra == 'dev'
Requires-Dist: mypy>=1.0.0; extra == 'dev'
Requires-Dist: pytest-asyncio>=0.21.0; extra == 'dev'
Requires-Dist: pytest-cov>=4.0.0; extra == 'dev'
Requires-Dist: pytest>=7.0.0; extra == 'dev'
Provides-Extra: http
Requires-Dist: httpx>=0.24.0; extra == 'http'
Provides-Extra: msgpack
Requires-Dist: msgpack>=1.0.0; extra == 'msgpack'
Provides-Extra: serialization
Requires-Dist: cbor2>=5.0.0; extra == 'serialization'
Requires-Dist: dicttoxml>=1.7.4; extra == 'serialization'
Requires-Dist: msgpack>=1.0.0; extra == 'serialization'
Requires-Dist: pymongo>=4.0.0; extra == 'serialization'
Requires-Dist: pyyaml>=6.0; extra == 'serialization'
Requires-Dist: tomli-w>=1.0.0; extra == 'serialization'
Requires-Dist: xmltodict>=0.12.0; extra == 'serialization'
Provides-Extra: toml
Requires-Dist: tomli-w>=1.0.0; extra == 'toml'
Provides-Extra: xml
Requires-Dist: dicttoxml>=1.7.4; extra == 'xml'
Requires-Dist: xmltodict>=0.12.0; extra == 'xml'
Provides-Extra: yaml
Requires-Dist: pyyaml>=6.0; extra == 'yaml'
